genbank/__init__.py
genbank/codons.py
genbank/feature.py
genbank/file.py
genbank/locus.py
genbank/meta.py
genbank/sequence.py
genbank/translate.py
genbank-0.121.data/scripts/genbank.py
genbank-0.121.dist-info/licenses/LICENSE
genbank-0.121.dist-info/METADATA
genbank-0.121.dist-info/WHEEL
genbank-0.121.dist-info/top_level.txt
genbank-0.121.dist-info/RECORD
